gytrash/__about__.py
gytrash/__init__.py
gytrash/filters/__init__.py
gytrash/filters/messenger.py
gytrash/formatters/__init__.py
gytrash/formatters/slack.py
gytrash/formatters/teams.py
gytrash/handlers/__init__.py
gytrash/handlers/slack.py
gytrash/handlers/teams.py
gytrash/logging_mixin.py
gytrash-0.0.22.dist-info/LICENSE
gytrash-0.0.22.dist-info/METADATA
gytrash-0.0.22.dist-info/WHEEL
gytrash-0.0.22.dist-info/RECORD
