Metadata-Version: 2.1
Name: gytrash
Version: 0.0.22
Summary: A python logging library with plugin integrations.
License: Apache 2.0
Author: Traey Hatch - trejas
Author-email: 4763901+trejas@users.noreply.github.com
Requires-Python: >=3.10.4,<4.0.0
Classifier: License :: Other/Proprietary License
Classifier: Programming Language :: Python :: 3
Classifier: Programming Language :: Python :: 3.11
Classifier: Programming Language :: Python :: 3.12
Requires-Dist: coloredlogs (==15.0.1)
Requires-Dist: requests (>=2.31.0,<3.0.0)
Requires-Dist: slack-sdk (==3.15.2)
Requires-Dist: sphinx (>=7.3.7,<8.0.0)
Requires-Dist: sphinx-material (>=0.0.36,<0.0.37)
